requestRender/__init__.py
requestRender/requestRender.py
requestRender-0.0.3.dist-info/METADATA
requestRender-0.0.3.dist-info/RECORD
requestRender-0.0.3.dist-info/WHEEL
requestRender-0.0.3.dist-info/top_level.txt
