Metadata-Version: 2.1
Name: requestRender
Version: 0.0.3
Summary: A PyPI package that provides a simple headless Selenium web browser for scraping wrapper around reactive websites.
Home-page: https://github.com/math-milan/requestRender
Maintainer: Milan Lovis Ramthun
Maintainer-email: dev.math.milan@gmail.com
Classifier: Programming Language :: Python :: 3
Classifier: Programming Language :: Python :: 3.7
Classifier: Programming Language :: Python :: 3.8
Classifier: Programming Language :: Python :: 3.9
Classifier: Programming Language :: Python :: 3.10
Classifier: Programming Language :: Python :: 3.11
Classifier: License :: OSI Approved :: MIT License
Classifier: Operating System :: OS Independent
License-File: LICENSE
Requires-Dist: chromedriver-autoinstaller
Requires-Dist: requests
Requires-Dist: selenium
